matchbox/__init__.py
matchbox/beads.py
matchbox/box.py
matchbox/colors.py
matchbox/config.py
matchbox/engine.py
matchbox_rl-1.0.0.dist-info/METADATA
matchbox_rl-1.0.0.dist-info/WHEEL
matchbox_rl-1.0.0.dist-info/licenses/LICENSE
matchbox_rl-1.0.0.dist-info/RECORD
