Metadata-Version: 2.4
Name: matchbox-rl
Version: 1.0.0
Summary: A tangible Reinforcement Learning engine with Matchboxes and colored Beads
Project-URL: Homepage, https://github.com/tctibbs/matchbox-rl
Project-URL: Repository, https://github.com/tctibbs/matchbox-rl
Author: Tristan Tibbs
License: MIT
License-File: LICENSE
Keywords: ai,education,machine-learning,matchbox,menace,reinforcement-learning
Classifier: Development Status :: 3 - Alpha
Classifier: Intended Audience :: Developers
Classifier: Intended Audience :: Education
Classifier: Intended Audience :: Science/Research
Classifier: License :: OSI Approved :: MIT License
Classifier: Programming Language :: Python :: 3
Classifier: Programming Language :: Python :: 3.10
Classifier: Programming Language :: Python :: 3.11
Classifier: Programming Language :: Python :: 3.12
Classifier: Programming Language :: Python :: 3.13
Classifier: Topic :: Scientific/Engineering :: Artificial Intelligence
Requires-Python: >=3.10
Provides-Extra: dev
Requires-Dist: pytest>=7.0; extra == 'dev'
Requires-Dist: ruff>=0.1.0; extra == 'dev'
